{"pageProps":{"article":{"_id":"656eb74b15c7a0ab9c227537","title":"San Diego Film Festival Showcases Local Talent","description":"The annual event highlights the creativity and skill of filmmakers in the region.","content":"The San Diego Film Festival, a beacon of cinematic brilliance in Southern California, recently showcased an extraordinary array of local talent. Celebrated for its eclectic mix of indie gems and blockbuster hits, the festival brought together filmmakers, actors, and enthusiasts in a vibrant celebration of the cinematic arts.\\\\n\\\\nSet against the backdrop of San Diego's stunning landscapes, the festival was a hub of creative exchange and inspiration. This year's lineup featured a compelling mix of feature films, documentaries, and short films, each telling unique stories with distinct voices and styles. The spotlight was on local filmmakers, giving them a platform to present their work to a wider audience and gain recognition in the industry.\\\\n\\\\nBeyond film screenings, the festival hosted a series of workshops, panels, and networking events. These gatherings provided emerging talent with invaluable opportunities to learn from seasoned professionals, discuss contemporary filmmaking trends, and forge connections that could shape their future careers. The San Diego Film Festival not only celebrated the art of filmmaking but also reinforced its commitment to nurturing local talent, fostering a community where creativity and collaboration thrive.","category":"Arts & Entertainment","source":"Film Spotlight","tags":["Film Festival","Local Talent","Entertainment"],"date":"2023-11-15","imgId":"6sv50x4gOPJvYar3lqsgU0","imgCreator":"Annie Spratt","cmsUrl":"//images.ctfassets.net/vdnl4md1xpsv/6sv50x4gOPJvYar3lqsgU0/23d24285d0aa9b2e7576859993580b32/annie-spratt-gHxFXoFT9J8-unsplash.jpg"}},"__N_SSG":true}